{
  "generatedAt": "2026-07-18T14:58:32.462Z",
  "source": "Open-Meteo · curated candidate stations",
  "isSample": false,
  "thermalShock": {
    "deltaC": 56.2,
    "deltaF": 101.2,
    "hotRef": "abs-hot",
    "coldRef": "abs-cold"
  },
  "records": [
    {
      "id": "abs-hot",
      "group": "temperature",
      "kind": "heat",
      "title": "Absolute Highest",
      "subtitle": "Hottest point on Earth",
      "value": 47.6,
      "unit": "°C",
      "display": "47.6°C",
      "displayImp": "117.7°F",
      "context": "117.7°F",
      "contextImp": "47.6°C",
      "location": {
        "name": "Basra",
        "region": "Basra",
        "country": "Iraq",
        "cc": "IQ",
        "lat": 30.51,
        "lon": 47.78
      },
      "observedAt": "2026-07-18T14:45:00.000Z",
      "source": "Open-Meteo",
      "ranking": [
        {
          "rank": 1,
          "name": "Basra",
          "region": "Basra",
          "country": "Iraq",
          "cc": "IQ",
          "value": 47.6,
          "display": "47.6°C",
          "displayImp": "117.7°F"
        },
        {
          "rank": 2,
          "name": "Ahvaz",
          "region": "Khuzestan",
          "country": "Iran",
          "cc": "IR",
          "value": 46.6,
          "display": "46.6°C",
          "displayImp": "115.9°F"
        },
        {
          "rank": 3,
          "name": "Bandar-e Mahshahr",
          "region": "Khuzestan",
          "country": "Iran",
          "cc": "IR",
          "value": 46.1,
          "display": "46.1°C",
          "displayImp": "115.0°F"
        },
        {
          "rank": 4,
          "name": "In Salah",
          "region": "Tamanrasset",
          "country": "Algeria",
          "cc": "DZ",
          "value": 45.7,
          "display": "45.7°C",
          "displayImp": "114.3°F"
        },
        {
          "rank": 5,
          "name": "Adrar",
          "region": "Adrar",
          "country": "Algeria",
          "cc": "DZ",
          "value": 45.6,
          "display": "45.6°C",
          "displayImp": "114.1°F"
        }
      ]
    },
    {
      "id": "abs-cold",
      "group": "temperature",
      "kind": "cold",
      "title": "Absolute Lowest",
      "subtitle": "Coldest point on Earth",
      "value": -8.6,
      "unit": "°C",
      "display": "-8.6°C",
      "displayImp": "16.5°F",
      "context": "16.5°F",
      "contextImp": "-8.6°C",
      "location": {
        "name": "Ushuaia",
        "region": "Tierra del Fuego",
        "country": "Argentina",
        "cc": "AR",
        "lat": -54.8,
        "lon": -68.3
      },
      "observedAt": "2026-07-18T14:45:00.000Z",
      "source": "Open-Meteo",
      "ranking": [
        {
          "rank": 1,
          "name": "Ushuaia",
          "region": "Tierra del Fuego",
          "country": "Argentina",
          "cc": "AR",
          "value": -8.6,
          "display": "-8.6°C",
          "displayImp": "16.5°F"
        },
        {
          "rank": 2,
          "name": "Punta Arenas",
          "region": "Magallanes",
          "country": "Chile",
          "cc": "CL",
          "value": -0.5,
          "display": "-0.5°C",
          "displayImp": "31.1°F"
        },
        {
          "rank": 3,
          "name": "Coyhaique",
          "region": "Aysén",
          "country": "Chile",
          "cc": "CL",
          "value": 1.1,
          "display": "1.1°C",
          "displayImp": "34.0°F"
        },
        {
          "rank": 4,
          "name": "Sarmiento",
          "region": "Chubut",
          "country": "Argentina",
          "cc": "AR",
          "value": 1.2,
          "display": "1.2°C",
          "displayImp": "34.2°F"
        },
        {
          "rank": 5,
          "name": "Comodoro Rivadavia",
          "region": "Chubut",
          "country": "Argentina",
          "cc": "AR",
          "value": 2.5,
          "display": "2.5°C",
          "displayImp": "36.5°F"
        }
      ]
    },
    {
      "id": "feels-hot",
      "group": "temperature",
      "kind": "feels",
      "title": "Most Dangerous Heat",
      "subtitle": "Highest feels-like temperature",
      "value": 43.7,
      "unit": "°C",
      "display": "43.7°C",
      "displayImp": "110.7°F",
      "context": "Feels like · 111°F",
      "contextImp": "Feels like · 44°C",
      "location": {
        "name": "Ahvaz",
        "region": "Khuzestan",
        "country": "Iran",
        "cc": "IR",
        "lat": 31.32,
        "lon": 48.67
      },
      "observedAt": "2026-07-18T14:45:00.000Z",
      "source": "Open-Meteo",
      "ranking": [
        {
          "rank": 1,
          "name": "Ahvaz",
          "region": "Khuzestan",
          "country": "Iran",
          "cc": "IR",
          "value": 43.7,
          "display": "43.7°C",
          "displayImp": "110.7°F"
        },
        {
          "rank": 2,
          "name": "Baghdad",
          "region": "Baghdad",
          "country": "Iraq",
          "cc": "IQ",
          "value": 42.9,
          "display": "42.9°C",
          "displayImp": "109.2°F"
        },
        {
          "rank": 3,
          "name": "Basra",
          "region": "Basra",
          "country": "Iraq",
          "cc": "IQ",
          "value": 42.8,
          "display": "42.8°C",
          "displayImp": "109.0°F"
        },
        {
          "rank": 4,
          "name": "Kuwait City",
          "region": "Al Asimah",
          "country": "Kuwait",
          "cc": "KW",
          "value": 42.6,
          "display": "42.6°C",
          "displayImp": "108.7°F"
        },
        {
          "rank": 5,
          "name": "Timbuktu",
          "region": "Tombouctou",
          "country": "Mali",
          "cc": "ML",
          "value": 41.9,
          "display": "41.9°C",
          "displayImp": "107.4°F"
        }
      ]
    },
    {
      "id": "city-hot",
      "group": "temperature",
      "kind": "heat",
      "title": "Hottest Major City",
      "subtitle": "Urban area over 1M people",
      "value": 47.6,
      "unit": "°C",
      "display": "47.6°C",
      "displayImp": "117.7°F",
      "context": "Pop. 1.4M",
      "contextImp": "Pop. 1.4M",
      "location": {
        "name": "Basra",
        "region": "Basra",
        "country": "Iraq",
        "cc": "IQ",
        "lat": 30.51,
        "lon": 47.78
      },
      "observedAt": "2026-07-18T14:45:00.000Z",
      "source": "Open-Meteo",
      "ranking": [
        {
          "rank": 1,
          "name": "Basra",
          "region": "Basra",
          "country": "Iraq",
          "cc": "IQ",
          "value": 47.6,
          "display": "47.6°C",
          "displayImp": "117.7°F"
        },
        {
          "rank": 2,
          "name": "Ahvaz",
          "region": "Khuzestan",
          "country": "Iran",
          "cc": "IR",
          "value": 46.6,
          "display": "46.6°C",
          "displayImp": "115.9°F"
        },
        {
          "rank": 3,
          "name": "Baghdad",
          "region": "Baghdad",
          "country": "Iraq",
          "cc": "IQ",
          "value": 45.1,
          "display": "45.1°C",
          "displayImp": "113.2°F"
        },
        {
          "rank": 4,
          "name": "Kuwait City",
          "region": "Al Asimah",
          "country": "Kuwait",
          "cc": "KW",
          "value": 44.1,
          "display": "44.1°C",
          "displayImp": "111.4°F"
        },
        {
          "rank": 5,
          "name": "Riyadh",
          "region": "Riyadh",
          "country": "Saudi Arabia",
          "cc": "SA",
          "value": 43.1,
          "display": "43.1°C",
          "displayImp": "109.6°F"
        }
      ]
    },
    {
      "id": "city-cold",
      "group": "temperature",
      "kind": "cold",
      "title": "Coldest Major City",
      "subtitle": "Urban area over 1M people",
      "value": 13.8,
      "unit": "°C",
      "display": "13.8°C",
      "displayImp": "56.8°F",
      "context": "Pop. 1.9M",
      "contextImp": "Pop. 1.9M",
      "location": {
        "name": "La Paz",
        "region": "La Paz",
        "country": "Bolivia",
        "cc": "BO",
        "lat": -16.5,
        "lon": -68.13
      },
      "observedAt": "2026-07-18T14:45:00.000Z",
      "source": "Open-Meteo",
      "ranking": [
        {
          "rank": 1,
          "name": "La Paz",
          "region": "La Paz",
          "country": "Bolivia",
          "cc": "BO",
          "value": 13.8,
          "display": "13.8°C",
          "displayImp": "56.8°F"
        },
        {
          "rank": 2,
          "name": "Quito",
          "region": "Pichincha",
          "country": "Ecuador",
          "cc": "EC",
          "value": 15.2,
          "display": "15.2°C",
          "displayImp": "59.4°F"
        },
        {
          "rank": 3,
          "name": "Ulaanbaatar",
          "region": "Ulaanbaatar",
          "country": "Mongolia",
          "cc": "MN",
          "value": 16.4,
          "display": "16.4°C",
          "displayImp": "61.5°F"
        },
        {
          "rank": 4,
          "name": "Bogotá",
          "region": "Cundinamarca",
          "country": "Colombia",
          "cc": "CO",
          "value": 18.3,
          "display": "18.3°C",
          "displayImp": "64.9°F"
        },
        {
          "rank": 5,
          "name": "Lima",
          "region": "Lima",
          "country": "Peru",
          "cc": "PE",
          "value": 21.9,
          "display": "21.9°C",
          "displayImp": "71.4°F"
        }
      ]
    },
    {
      "id": "anomaly-hot",
      "group": "temperature",
      "kind": "heat",
      "title": "Hottest vs Normal",
      "subtitle": "vs June average",
      "value": 9.1,
      "unit": "°C",
      "display": "+9.1°C",
      "displayImp": "+16.4°F",
      "context": "46°C now · 37°C normal",
      "contextImp": "114°F now · 98°F normal",
      "location": {
        "name": "Adrar",
        "region": "Adrar",
        "country": "Algeria",
        "cc": "DZ",
        "lat": 27.87,
        "lon": -0.29
      },
      "observedAt": "2026-07-18T14:45:00.000Z",
      "source": "Open-Meteo",
      "ranking": [
        {
          "rank": 1,
          "name": "Adrar",
          "region": "Adrar",
          "country": "Algeria",
          "cc": "DZ",
          "value": 9.1,
          "display": "+9.1°C",
          "displayImp": "+16.4°F"
        },
        {
          "rank": 2,
          "name": "In Salah",
          "region": "Tamanrasset",
          "country": "Algeria",
          "cc": "DZ",
          "value": 8.7,
          "display": "+8.7°C",
          "displayImp": "+15.7°F"
        },
        {
          "rank": 3,
          "name": "Baghdad",
          "region": "Baghdad",
          "country": "Iraq",
          "cc": "IQ",
          "value": 8.6,
          "display": "+8.6°C",
          "displayImp": "+15.5°F"
        },
        {
          "rank": 4,
          "name": "Basra",
          "region": "Basra",
          "country": "Iraq",
          "cc": "IQ",
          "value": 8.5,
          "display": "+8.5°C",
          "displayImp": "+15.3°F"
        },
        {
          "rank": 5,
          "name": "Bandar-e Mahshahr",
          "region": "Khuzestan",
          "country": "Iran",
          "cc": "IR",
          "value": 7.7,
          "display": "+7.7°C",
          "displayImp": "+13.9°F"
        }
      ]
    },
    {
      "id": "anomaly-cold",
      "group": "temperature",
      "kind": "cold",
      "title": "Coldest vs Normal",
      "subtitle": "vs June average",
      "value": -9.1,
      "unit": "°C",
      "display": "-9.1°C",
      "displayImp": "-16.4°F",
      "context": "-9°C now · 1°C normal",
      "contextImp": "17°F now · 33°F normal",
      "location": {
        "name": "Ushuaia",
        "region": "Tierra del Fuego",
        "country": "Argentina",
        "cc": "AR",
        "lat": -54.8,
        "lon": -68.3
      },
      "observedAt": "2026-07-18T14:45:00.000Z",
      "source": "Open-Meteo",
      "ranking": [
        {
          "rank": 1,
          "name": "Ushuaia",
          "region": "Tierra del Fuego",
          "country": "Argentina",
          "cc": "AR",
          "value": -9.1,
          "display": "-9.1°C",
          "displayImp": "-16.4°F"
        },
        {
          "rank": 2,
          "name": "Comodoro Rivadavia",
          "region": "Chubut",
          "country": "Argentina",
          "cc": "AR",
          "value": -4.3,
          "display": "-4.3°C",
          "displayImp": "-7.7°F"
        },
        {
          "rank": 3,
          "name": "Punta Arenas",
          "region": "Magallanes",
          "country": "Chile",
          "cc": "CL",
          "value": -3.2,
          "display": "-3.2°C",
          "displayImp": "-5.8°F"
        },
        {
          "rank": 4,
          "name": "Marble Bar",
          "region": "Western Australia",
          "country": "Australia",
          "cc": "AU",
          "value": -2.5,
          "display": "-2.5°C",
          "displayImp": "-4.5°F"
        },
        {
          "rank": 5,
          "name": "Singapore",
          "region": "Singapore",
          "country": "Singapore",
          "cc": "SG",
          "value": -2.5,
          "display": "-2.5°C",
          "displayImp": "-4.5°F"
        }
      ]
    },
    {
      "id": "humid-high",
      "group": "atmosphere",
      "kind": "humid",
      "title": "Most Saturated",
      "subtitle": "Highest dew point",
      "value": 27.2,
      "unit": "°C",
      "display": "27°C",
      "displayImp": "81°F",
      "context": "Dew point",
      "contextImp": "Dew point",
      "location": {
        "name": "Jask",
        "region": "Hormozgan",
        "country": "Iran",
        "cc": "IR",
        "lat": 25.64,
        "lon": 57.77
      },
      "observedAt": "2026-07-18T14:45:00.000Z",
      "source": "Open-Meteo",
      "ranking": [
        {
          "rank": 1,
          "name": "Jask",
          "region": "Hormozgan",
          "country": "Iran",
          "cc": "IR",
          "value": 27.2,
          "display": "27°C",
          "displayImp": "81°F"
        },
        {
          "rank": 2,
          "name": "Dubai",
          "region": "Dubai",
          "country": "United Arab Emirates",
          "cc": "AE",
          "value": 26.6,
          "display": "27°C",
          "displayImp": "80°F"
        },
        {
          "rank": 3,
          "name": "Kolkata",
          "region": "West Bengal",
          "country": "India",
          "cc": "IN",
          "value": 25.3,
          "display": "25°C",
          "displayImp": "78°F"
        },
        {
          "rank": 4,
          "name": "Dhaka",
          "region": "Dhaka",
          "country": "Bangladesh",
          "cc": "BD",
          "value": 25,
          "display": "25°C",
          "displayImp": "77°F"
        },
        {
          "rank": 5,
          "name": "Mumbai",
          "region": "Maharashtra",
          "country": "India",
          "cc": "IN",
          "value": 24.7,
          "display": "25°C",
          "displayImp": "76°F"
        }
      ]
    },
    {
      "id": "humid-low",
      "group": "atmosphere",
      "kind": "dry",
      "title": "Driest Air",
      "subtitle": "Lowest relative humidity",
      "value": 5,
      "unit": "%",
      "display": "5%",
      "displayImp": "5%",
      "context": "Relative humidity",
      "contextImp": "Relative humidity",
      "location": {
        "name": "In Salah",
        "region": "Tamanrasset",
        "country": "Algeria",
        "cc": "DZ",
        "lat": 27.19,
        "lon": 2.46
      },
      "observedAt": "2026-07-18T14:45:00.000Z",
      "source": "Open-Meteo",
      "ranking": [
        {
          "rank": 1,
          "name": "In Salah",
          "region": "Tamanrasset",
          "country": "Algeria",
          "cc": "DZ",
          "value": 5,
          "display": "5%",
          "displayImp": "5%"
        },
        {
          "rank": 2,
          "name": "Adrar",
          "region": "Adrar",
          "country": "Algeria",
          "cc": "DZ",
          "value": 5,
          "display": "5%",
          "displayImp": "5%"
        },
        {
          "rank": 3,
          "name": "Basra",
          "region": "Basra",
          "country": "Iraq",
          "cc": "IQ",
          "value": 7,
          "display": "7%",
          "displayImp": "7%"
        },
        {
          "rank": 4,
          "name": "Riyadh",
          "region": "Riyadh",
          "country": "Saudi Arabia",
          "cc": "SA",
          "value": 7,
          "display": "7%",
          "displayImp": "7%"
        },
        {
          "rank": 5,
          "name": "Bandar-e Mahshahr",
          "region": "Khuzestan",
          "country": "Iran",
          "cc": "IR",
          "value": 7,
          "display": "7%",
          "displayImp": "7%"
        }
      ]
    },
    {
      "id": "precip",
      "group": "atmosphere",
      "kind": "precip",
      "title": "Heaviest Rainfall",
      "subtitle": "Accumulated last hour",
      "value": 0.6,
      "unit": "mm",
      "display": "0.6 mm",
      "displayImp": "0.02 in",
      "context": "Rainfall · last hour",
      "contextImp": "Rainfall · last hour",
      "location": {
        "name": "Cherrapunji",
        "region": "Meghalaya",
        "country": "India",
        "cc": "IN",
        "lat": 25.27,
        "lon": 91.73
      },
      "observedAt": "2026-07-18T14:45:00.000Z",
      "source": "Open-Meteo",
      "ranking": [
        {
          "rank": 1,
          "name": "Cherrapunji",
          "region": "Meghalaya",
          "country": "India",
          "cc": "IN",
          "value": 0.6,
          "display": "0.6 mm",
          "displayImp": "0.02 in"
        },
        {
          "rank": 2,
          "name": "Murmansk",
          "region": "Murmansk Oblast",
          "country": "Russia",
          "cc": "RU",
          "value": 0.5,
          "display": "0.5 mm",
          "displayImp": "0.02 in"
        },
        {
          "rank": 3,
          "name": "Mawsynram",
          "region": "Meghalaya",
          "country": "India",
          "cc": "IN",
          "value": 0.5,
          "display": "0.5 mm",
          "displayImp": "0.02 in"
        },
        {
          "rank": 4,
          "name": "Mumbai",
          "region": "Maharashtra",
          "country": "India",
          "cc": "IN",
          "value": 0.2,
          "display": "0.2 mm",
          "displayImp": "0.01 in"
        },
        {
          "rank": 5,
          "name": "Verkhoyansk",
          "region": "Sakha Republic",
          "country": "Russia",
          "cc": "RU",
          "value": 0.1,
          "display": "0.1 mm",
          "displayImp": "0.00 in"
        }
      ]
    },
    {
      "id": "snow",
      "group": "atmosphere",
      "kind": "snow",
      "title": "Deepest Snowpack",
      "subtitle": "Most snow on the ground",
      "value": 0.07,
      "unit": "m",
      "display": "0.07 m",
      "displayImp": "0.23 ft",
      "context": "Snow & firn on the ground",
      "contextImp": "Snow & firn on the ground",
      "location": {
        "name": "Ushuaia",
        "region": "Tierra del Fuego",
        "country": "Argentina",
        "cc": "AR",
        "lat": -54.8,
        "lon": -68.3
      },
      "observedAt": "2026-07-18T14:45:00.000Z",
      "source": "Open-Meteo",
      "ranking": [
        {
          "rank": 1,
          "name": "Ushuaia",
          "region": "Tierra del Fuego",
          "country": "Argentina",
          "cc": "AR",
          "value": 0.07,
          "display": "0.07 m",
          "displayImp": "0.23 ft"
        },
        {
          "rank": 2,
          "name": "Coyhaique",
          "region": "Aysén",
          "country": "Chile",
          "cc": "CL",
          "value": 0.07,
          "display": "0.07 m",
          "displayImp": "0.23 ft"
        },
        {
          "rank": 3,
          "name": "Punta Arenas",
          "region": "Magallanes",
          "country": "Chile",
          "cc": "CL",
          "value": 0.02,
          "display": "0.02 m",
          "displayImp": "0.07 ft"
        },
        {
          "rank": 4,
          "name": "Sarmiento",
          "region": "Chubut",
          "country": "Argentina",
          "cc": "AR",
          "value": 0.01,
          "display": "0.01 m",
          "displayImp": "0.03 ft"
        }
      ]
    },
    {
      "id": "wind",
      "group": "atmosphere",
      "kind": "wind",
      "title": "Strongest Wind",
      "subtitle": "Highest active gust",
      "value": 57.2,
      "unit": "km/h",
      "display": "57 km/h",
      "displayImp": "36 mph",
      "context": "Peak gust · last hour",
      "contextImp": "Peak gust · last hour",
      "location": {
        "name": "Adrar",
        "region": "Adrar",
        "country": "Algeria",
        "cc": "DZ",
        "lat": 27.87,
        "lon": -0.29
      },
      "observedAt": "2026-07-18T14:45:00.000Z",
      "source": "Open-Meteo",
      "ranking": [
        {
          "rank": 1,
          "name": "Adrar",
          "region": "Adrar",
          "country": "Algeria",
          "cc": "DZ",
          "value": 57.2,
          "display": "57 km/h",
          "displayImp": "36 mph"
        },
        {
          "rank": 2,
          "name": "In Salah",
          "region": "Tamanrasset",
          "country": "Algeria",
          "cc": "DZ",
          "value": 52.2,
          "display": "52 km/h",
          "displayImp": "32 mph"
        },
        {
          "rank": 3,
          "name": "Mecca",
          "region": "Makkah",
          "country": "Saudi Arabia",
          "cc": "SA",
          "value": 51.8,
          "display": "52 km/h",
          "displayImp": "32 mph"
        },
        {
          "rank": 4,
          "name": "Nawabshah",
          "region": "Sindh",
          "country": "Pakistan",
          "cc": "PK",
          "value": 49,
          "display": "49 km/h",
          "displayImp": "30 mph"
        },
        {
          "rank": 5,
          "name": "Aswan",
          "region": "Aswan",
          "country": "Egypt",
          "cc": "EG",
          "value": 43.6,
          "display": "44 km/h",
          "displayImp": "27 mph"
        }
      ]
    },
    {
      "id": "aqi-clean",
      "group": "atmosphere",
      "kind": "clean",
      "title": "Cleanest Air",
      "subtitle": "Lowest air quality index",
      "value": 18,
      "unit": "AQI",
      "display": "AQI 18",
      "displayImp": "AQI 18",
      "context": "Good · clean",
      "contextImp": "Good · clean",
      "location": {
        "name": "La Rinconada",
        "region": "Puno",
        "country": "Peru",
        "cc": "PE",
        "lat": -14.63,
        "lon": -69.44
      },
      "observedAt": "2026-07-18T14:00:00.000Z",
      "source": "Open-Meteo AQ",
      "ranking": [
        {
          "rank": 1,
          "name": "La Rinconada",
          "region": "Puno",
          "country": "Peru",
          "cc": "PE",
          "value": 18,
          "display": "AQI 18",
          "displayImp": "AQI 18"
        },
        {
          "rank": 2,
          "name": "Verkhoyansk",
          "region": "Sakha Republic",
          "country": "Russia",
          "cc": "RU",
          "value": 19,
          "display": "AQI 19",
          "displayImp": "AQI 19"
        },
        {
          "rank": 3,
          "name": "Comodoro Rivadavia",
          "region": "Chubut",
          "country": "Argentina",
          "cc": "AR",
          "value": 21,
          "display": "AQI 21",
          "displayImp": "AQI 21"
        },
        {
          "rank": 4,
          "name": "Bariloche",
          "region": "Río Negro (Andes)",
          "country": "Argentina",
          "cc": "AR",
          "value": 21,
          "display": "AQI 21",
          "displayImp": "AQI 21"
        },
        {
          "rank": 5,
          "name": "Coyhaique",
          "region": "Aysén",
          "country": "Chile",
          "cc": "CL",
          "value": 22,
          "display": "AQI 22",
          "displayImp": "AQI 22"
        }
      ]
    },
    {
      "id": "aqi-dirty",
      "group": "atmosphere",
      "kind": "hazard",
      "title": "Most Hazardous Air",
      "subtitle": "Highest air quality index",
      "value": 803,
      "unit": "AQI",
      "display": "AQI 803",
      "displayImp": "AQI 803",
      "context": "Hazardous",
      "contextImp": "Hazardous",
      "location": {
        "name": "Nawabshah",
        "region": "Sindh",
        "country": "Pakistan",
        "cc": "PK",
        "lat": 26.24,
        "lon": 68.41
      },
      "observedAt": "2026-07-18T14:00:00.000Z",
      "source": "Open-Meteo AQ",
      "ranking": [
        {
          "rank": 1,
          "name": "Nawabshah",
          "region": "Sindh",
          "country": "Pakistan",
          "cc": "PK",
          "value": 803,
          "display": "AQI 803",
          "displayImp": "AQI 803"
        },
        {
          "rank": 2,
          "name": "Delhi",
          "region": "Delhi",
          "country": "India",
          "cc": "IN",
          "value": 658,
          "display": "AQI 658",
          "displayImp": "AQI 658"
        },
        {
          "rank": 3,
          "name": "Riyadh",
          "region": "Riyadh",
          "country": "Saudi Arabia",
          "cc": "SA",
          "value": 623,
          "display": "AQI 623",
          "displayImp": "AQI 623"
        },
        {
          "rank": 4,
          "name": "In Salah",
          "region": "Tamanrasset",
          "country": "Algeria",
          "cc": "DZ",
          "value": 270,
          "display": "AQI 270",
          "displayImp": "AQI 270"
        },
        {
          "rank": 5,
          "name": "Adrar",
          "region": "Adrar",
          "country": "Algeria",
          "cc": "DZ",
          "value": 189,
          "display": "AQI 189",
          "displayImp": "AQI 189"
        }
      ]
    }
  ],
  "sweetSpot": {
    "title": "Where to Be Right Now",
    "display": "93",
    "score": 93.2,
    "context": "Feels 24°C · AQI 43 · 44% humidity · daytime",
    "location": {
      "name": "Denver",
      "region": "",
      "country": "United States",
      "cc": "US",
      "lat": 39.74,
      "lon": -104.99
    },
    "observedAt": "2026-07-18T14:58:32.628Z",
    "source": "Open-Meteo",
    "ranking": [
      {
        "rank": 1,
        "name": "Denver",
        "country": "United States",
        "cc": "US",
        "score": 93.2,
        "display": "93",
        "feels": 24,
        "aqi": 43,
        "humidity": 44,
        "isDay": true
      },
      {
        "rank": 2,
        "name": "Munich",
        "country": "Germany",
        "cc": "DE",
        "score": 89.7,
        "display": "90",
        "feels": 24,
        "aqi": 42,
        "humidity": 42,
        "isDay": true
      },
      {
        "rank": 3,
        "name": "Copenhagen",
        "country": "Denmark",
        "cc": "DK",
        "score": 87.3,
        "display": "87",
        "feels": 21,
        "aqi": 52,
        "humidity": 41,
        "isDay": true
      },
      {
        "rank": 4,
        "name": "Nairobi",
        "country": "Kenya",
        "cc": "KE",
        "score": 86.5,
        "display": "87",
        "feels": 23,
        "aqi": 82,
        "humidity": 45,
        "isDay": true
      },
      {
        "rank": 5,
        "name": "Antananarivo",
        "country": "Madagascar",
        "cc": "MG",
        "score": 85.4,
        "display": "85",
        "feels": 19,
        "aqi": 54,
        "humidity": 48,
        "isDay": false
      }
    ]
  }
}
